PyZufall-0.13.2.dist-info/DESCRIPTION.rst
PyZufall-0.13.2.dist-info/METADATA
PyZufall-0.13.2.dist-info/RECORD
PyZufall-0.13.2.dist-info/WHEEL
PyZufall-0.13.2.dist-info/metadata.json
PyZufall-0.13.2.dist-info/top_level.txt
pyzufall/__init__.py
pyzufall/generator.py
pyzufall/helfer.py
pyzufall/person.py
pyzufall/satz.py
pyzufall/version.py
pyzufall/data/adjektiv.txt
pyzufall/data/baeume.txt
pyzufall/data/berufe.txt
pyzufall/data/ditransitive_verben.txt
pyzufall/data/email_domains.txt
pyzufall/data/gegenstaende.txt
pyzufall/data/geschmack.txt
pyzufall/data/interessen.txt
pyzufall/data/intransitive_verben.txt
pyzufall/data/intransitive_verben_2.txt
pyzufall/data/koerperteile.txt
pyzufall/data/musikgenre.txt
pyzufall/data/nachnamen.txt
pyzufall/data/nahrung.txt
pyzufall/data/nebensatz.txt
pyzufall/data/nullwertige_verben.txt
pyzufall/data/ort.txt
pyzufall/data/pflanzen.txt
pyzufall/data/sprichwoerter.txt
pyzufall/data/stadt_bundesland.txt
pyzufall/data/tiere.txt
pyzufall/data/transitive_verben.txt
pyzufall/data/transitive_verben_2.txt
pyzufall/data/vornamen_m.txt
pyzufall/data/vornamen_w.txt
