Metadata-Version: 2.0
Name: PyZufall
Version: 0.13.2
Summary: 
Requires-Dist: future
